commercetxt/__init__.py
commercetxt/async_parser.py
commercetxt/bridge.py
commercetxt/cache.py
commercetxt/catalog_filters_validator.py
commercetxt/cli.py
commercetxt/constants.py
commercetxt/enhanced_variants_validator.py
commercetxt/limits.py
commercetxt/logging_config.py
commercetxt/metrics.py
commercetxt/model.py
commercetxt/parser.py
commercetxt/py.typed
commercetxt/resolver.py
commercetxt/security.py
commercetxt/validator.py
commercetxt/rag/__init__.py
commercetxt/rag/async_pipeline.py
commercetxt/rag/container.py
commercetxt/rag/exceptions.py
commercetxt/rag/metrics.py
commercetxt/rag/pipeline.py
commercetxt/rag/core/__init__.py
commercetxt/rag/core/constants.py
commercetxt/rag/core/filters.py
commercetxt/rag/core/generator.py
commercetxt/rag/core/rate_limiter.py
commercetxt/rag/core/semantic_tags.py
commercetxt/rag/core/shards.py
commercetxt/rag/core/caching/__init__.py
commercetxt/rag/core/caching/base_cache.py
commercetxt/rag/core/caching/embedding_cache.py
commercetxt/rag/core/caching/search_cache.py
commercetxt/rag/core/caching/slm_cache.py
commercetxt/rag/drivers/__init__.py
commercetxt/rag/drivers/async_faiss_store.py
commercetxt/rag/drivers/async_openai_embedder.py
commercetxt/rag/drivers/async_redis_storage.py
commercetxt/rag/drivers/faiss_store.py
commercetxt/rag/drivers/local_embedder.py
commercetxt/rag/drivers/local_storage.py
commercetxt/rag/drivers/openai_embedder.py
commercetxt/rag/drivers/pinecone_store.py
commercetxt/rag/drivers/qdrant_store.py
commercetxt/rag/drivers/redis_storage.py
commercetxt/rag/drivers/slm_tagger.py
commercetxt/rag/interfaces/__init__.py
commercetxt/rag/interfaces/async_embedder.py
commercetxt/rag/interfaces/async_storage.py
commercetxt/rag/interfaces/async_vector_store.py
commercetxt/rag/interfaces/base_embedder.py
commercetxt/rag/interfaces/base_storage.py
commercetxt/rag/interfaces/base_vector_store.py
commercetxt/rag/monitoring/__init__.py
commercetxt/rag/monitoring/health.py
commercetxt/rag/tools/__init__.py
commercetxt-1.0.3.dist-info/METADATA
commercetxt-1.0.3.dist-info/WHEEL
commercetxt-1.0.3.dist-info/entry_points.txt
commercetxt-1.0.3.dist-info/top_level.txt
commercetxt-1.0.3.dist-info/RECORD
