Metadata-Version: 2.4
Name: commercetxt
Version: 1.0.3
Summary: Python reference parser + RAG tools for the CommerceTXT protocol.
Author-email: Tsanko Zanov <hello@commercetxt.org>
License-Expression: MIT
Project-URL: Homepage, https://commercetxt.org
Project-URL: Specification, https://github.com/commercetxt/commercetxt/tree/main/spec
Project-URL: Documentation, https://github.com/commercetxt/commercetxt/tree/main/parsers/python
Project-URL: Quickstart, https://github.com/commercetxt/commercetxt#quickstart
Project-URL: Repository, https://github.com/commercetxt/commercetxt
Project-URL: Issues, https://github.com/commercetxt/commercetxt/issues
Project-URL: Changelog, https://github.com/commercetxt/commercetxt/releases
Keywords: commercetxt,protocol,ecommerce,ai,llm,rag,shopping,product-feed,schema-org,json-ld,agents,inventory,pricing,realtime,grounding,catalog
Classifier: Development Status :: 4 - Beta
Classifier: Intended Audience :: Developers
Classifier: Operating System :: OS Independent
Classifier: Programming Language :: Python :: 3
Classifier: Programming Language :: Python :: 3 :: Only
Classifier: Programming Language :: Python :: 3.10
Classifier: Programming Language :: Python :: 3.11
Classifier: Programming Language :: Python :: 3.12
Classifier: Programming Language :: Python :: 3.13
Classifier: Topic :: Internet :: WWW/HTTP :: Dynamic Content
Classifier: Topic :: Software Development :: Libraries
Classifier: Topic :: Scientific/Engineering :: Artificial Intelligence
Classifier: Typing :: Typed
Requires-Python: >=3.10
Provides-Extra: cli
Requires-Dist: colorama>=0.4.6; extra == "cli"
Provides-Extra: async
Requires-Dist: aiofiles>=23.0.0; extra == "async"
Provides-Extra: dev
Requires-Dist: pytest>=7.0; extra == "dev"
Requires-Dist: pytest-asyncio>=0.23; extra == "dev"
Requires-Dist: pytest-cov>=4.0; extra == "dev"
Requires-Dist: hypothesis>=6.0; extra == "dev"
Requires-Dist: black>=24.0; extra == "dev"
Requires-Dist: mypy>=1.7; extra == "dev"
Requires-Dist: ruff>=0.5; extra == "dev"
Provides-Extra: rag-local
Requires-Dist: sentence-transformers>=2.2.0; extra == "rag-local"
Provides-Extra: rag-openai
Requires-Dist: openai>=1.0.0; extra == "rag-openai"
Provides-Extra: rag-faiss
Requires-Dist: faiss-cpu; extra == "rag-faiss"
Requires-Dist: numpy>=1.24; extra == "rag-faiss"
Provides-Extra: rag-qdrant
Requires-Dist: qdrant-client>=1.7.0; extra == "rag-qdrant"
Provides-Extra: rag-pinecone
Requires-Dist: pinecone>=5.0.0; extra == "rag-pinecone"
Provides-Extra: rag-redis
Requires-Dist: redis>=5.0.0; extra == "rag-redis"
Provides-Extra: rag
Requires-Dist: sentence-transformers>=2.2.0; extra == "rag"
Requires-Dist: faiss-cpu; extra == "rag"
Requires-Dist: numpy>=1.24; extra == "rag"
Requires-Dist: redis>=5.0.0; extra == "rag"
Provides-Extra: rag-all
Requires-Dist: openai>=1.0.0; extra == "rag-all"
Requires-Dist: sentence-transformers>=2.2.0; extra == "rag-all"
Requires-Dist: pinecone>=5.0.0; extra == "rag-all"
Requires-Dist: qdrant-client>=1.7.0; extra == "rag-all"
Requires-Dist: faiss-cpu; extra == "rag-all"
Requires-Dist: numpy>=1.24; extra == "rag-all"
Requires-Dist: redis>=5.0.0; extra == "rag-all"
